ethfinex/__init__.py
ethfinex/main.py
ethfinex_python-0.0.1.dist-info/LICENSE
ethfinex_python-0.0.1.dist-info/METADATA
ethfinex_python-0.0.1.dist-info/WHEEL
ethfinex_python-0.0.1.dist-info/top_level.txt
ethfinex_python-0.0.1.dist-info/RECORD
