Metadata-Version: 2.1
Name: ethfinex-python
Version: 0.0.1
Summary: An unofficial python wrapper for the Ethfinex exchange
Home-page: https://github.com/shanefontaine/ethfinex
Author: Shane Fontaine
Author-email: shane6fontaine@gmail.com
License: UNKNOWN
Platform: UNKNOWN
Classifier: Programming Language :: Python :: 3.6
Classifier: License :: OSI Approved :: MIT License
Classifier: Operating System :: OS Independent
